molann/__init__.py
molann/ann.py
molann/feature.py
molann-1.1.7.dist-info/LICENSE
molann-1.1.7.dist-info/METADATA
molann-1.1.7.dist-info/WHEEL
molann-1.1.7.dist-info/top_level.txt
molann-1.1.7.dist-info/RECORD
