Metadata-Version: 2.1
Name: molann
Version: 1.1.7
Summary: "PyTorch Artificial Neural Networks (ANNs) for Molecular Systems",
Home-page: https://github.com/zwpku/molann
Author: Wei Zhang
Author-email: wzhangpku@gmail.com
Project-URL: Bug Tracker, https://github.com/zwpku/molann/issues
Classifier: Programming Language :: Python :: 3
Classifier: License :: OSI Approved :: MIT License
Classifier: Operating System :: Unix
Requires-Python: >=3.7
License-File: LICENSE
Requires-Dist: torch (>=1.10.0)
Requires-Dist: mdanalysis (>=2.0.0)
Requires-Dist: numpy (>=1.20.3)
Requires-Dist: pandas (>=1.3.5)
